Workbook

Sheet 📊 Dashboard
A1: THE BRADLEY PROJECT LLC — Business Finance Tracker
A2: ⚡ Blue cells = you type here | Black cells = auto-calculated | Green cells = pulled from other sheets
A4: SETTINGS — Change these to update the whole dashboard
A5: Current Year: | B5: 2026 | C5: Current Month (1-12): | D5: 6 | E5: Tax Rate: | F5: 0.3 | G5: Reinvest Rate: | H5: 0.15
A7: THIS MONTH — Your numbers at a glance
A8: GROSS REVENUE | B8: TAXES OWED | C8: OPERATING COSTS | D8: REINVESTMENT | E8: YOUR PAY | F8: TAX SAVED | G8: RESERVE FUND | H8: NET PROFIT MARGIN
A9: =IFERROR(SUMPRODUCT((MONTH('📥 Income Log'!A:A)=D5)*(YEAR('📥 Income Log'!A:A)=B5)*'📥 Income Log'!D:D),0) -> 0 | B9: =A9*F5 -> 0 | C9: =IFERROR(SUMPRODUCT((MONTH('💸 Expense Log'!A:A)=D5)*(YEAR('💸 Expense Log'!A:A)=B5)*'💸 Expense Log'!D:D),0) -> 0 | D9: =(A9-B9-C9)*H5 -> 0 | E9: =A9-B9-C9-D9 -> 0 | F9: =IFERROR(SUMPRODUCT((MONTH('🪣 Tax Tracker'!A:A)=D5)*(YEAR('🪣 Tax Tracker'!A:A)=B5)*'🪣 Tax Tracker'!C:C),0) -> 0 | G9: =IFERROR(SUM('🏦 Reserve Fund'!C:C),0) -> 200 | H9: =IFERROR(E9/A9,0) -> 0
A11: YEAR TO DATE — Total since January 1
A12: YTD Revenue | B12: YTD Taxes Owed | C12: YTD Expenses | D12: YTD Reinvested | E12: YTD Take-Home | F12: YTD Tax Saved | G12: Reserve Balance | H12: YTD Profit Margin
A13: =IFERROR(SUMPRODUCT((YEAR('📥 Income Log'!A:A)=B5)*'📥 Income Log'!D:D),0) -> 0 | B13: =A13*F5 -> 0 | C13: =IFERROR(SUMPRODUCT((YEAR('💸 Expense Log'!A:A)=B5)*'💸 Expense Log'!D:D),0) -> 0 | D13: =(A13-B13-C13)*H5 -> 0 | E13: =A13-B13-C13-D13 -> 0 | F13: =IFERROR(SUM('🪣 Tax Tracker'!C:C),0) -> 245.84 | G13: =G9 -> 200 | H13: =IFERROR(E13/A13,0) -> 0
A15: QUARTERLY TAX CALENDAR — Save 30% every deposit, pay quarterly
A16: Quarter | B16: Period | C16: Due Date | D16: Estimated Owed | E16: Paid? | F16: Amount Paid | G16: Balance Due | H16: Status
A17: Q1 | B17: Jan – Mar | C17: April 15 | D17: =IFERROR(SUMPRODUCT((MONTH('📥 Income Log'!A:A)>=1)*(MONTH('📥 Income Log'!A:A)<=3)*(YEAR('📥 Income Log'!A:A)=B5)*'📥 Income Log'!D:D)*F5,0) -> 0 | E17: No | F17: 0 | G17: =D17-F17 -> 0 | H17: =IF(E17="Yes","✅ PAID",IF(D17=0,"—","⚠️ DUE")) -> —
A18: Q2 | B18: Apr – May | C18: June 15 | D18: =IFERROR(SUMPRODUCT((MONTH('📥 Income Log'!A:A)>=4)*(MONTH('📥 Income Log'!A:A)<=5)*(YEAR('📥 Income Log'!A:A)=B5)*'📥 Income Log'!D:D)*F5,0) -> 0 | E18: No | F18: 0 | G18: =D18-F18 -> 0 | H18: =IF(E18="Yes","✅ PAID",IF(D18=0,"—","⚠️ DUE")) -> —
A19: Q3 | B19: Jun – Aug | C19: September 15 | D19: =IFERROR(SUMPRODUCT((MONTH('📥 Income Log'!A:A)>=6)*(MONTH('📥 Income Log'!A:A)<=8)*(YEAR('📥 Income Log'!A:A)=B5)*'📥 Income Log'!D:D)*F5,0) -> 0 | E19: No | F19: 0 | G19: =D19-F19 -> 0 | H19: =IF(E19="Yes","✅ PAID",IF(D19=0,"—","⚠️ DUE")) -> —
A20: Q4 | B20: Sep – Dec | C20: January 15 | D20: =IFERROR(SUMPRODUCT((MONTH('📥 Income Log'!A:A)>=9)*(MONTH('📥 Income Log'!A:A)<=12)*(YEAR('📥 Income Log'!A:A)=B5)*'📥 Income Log'!D:D)*F5,0) -> 0 | E20: No | F20: 0 | G20: =D20-F20 -> 0 | H20: =IF(E20="Yes","✅ PAID",IF(D20=0,"—","⚠️ DUE")) -> —
A22: HOW TO USE THIS TRACKER
A23: 1. Log every payment you receive in '📥 Income Log' — date, source, amount.
A24: 2. Log every business expense in '💸 Expense Log' — date, category, vendor, amount.
A25: 3. Every time money comes in, move 30% to your tax savings account immediately.
A26: 4. Log that transfer in '🪣 Tax Tracker' so the dashboard stays accurate.
A27: 5. When you pay yourself, log it in '💰 Owner Draw'.
A28: 6. Check this dashboard once a week. 15 minutes. Make one decision.
A29: 7. Do NOT touch the Tax Tracker bucket. That money belongs to the IRS.

Sheet 📥 Income Log
A1: 📥 INCOME LOG — Log every dollar that comes into the business
A2: Blue cells = you type here | One row per payment received
A3: DATE | B3: SOURCE | C3: DESCRIPTION | D3: AMOUNT ($) | E3: PAYMENT METHOD | F3: MONTH | G3: NOTES
A4: 46174 | B4: Ticket Fees | C4: Pride Night @ Club XYZ — 45 tickets | D4: 337.5 | E4: Stripe | F4: =IFERROR(TEXT(A4,"MMM YYYY"),"") -> Jun 2026
A5: 46176 | B5: Marketplace Fees | C5: Costume commission — performer Jade | D5: 24 | E5: Stripe | F5: =IFERROR(TEXT(A5,"MMM YYYY"),"") -> Jun 2026
A6: 46181 | B6: Book Royalties | C6: Amazon KDP — May royalties | D6: 48.22 | E6: Direct Deposit | F6: =IFERROR(TEXT(A6,"MMM YYYY"),"") -> Jun 2026
A7: 46188 | B7: Ticket Fees | C7: Drag Brunch @ Rose City — 22 tickets | D7: 165 | E7: Stripe | F7: =IFERROR(TEXT(A7,"MMM YYYY"),"") -> Jun 2026
F8: =IFERROR(TEXT(A8,"MMM YYYY"),"") -> Dec 1899
F9: =IFERROR(TEXT(A9,"MMM YYYY"),"") -> Dec 1899
F10: =IFERROR(TEXT(A10,"MMM YYYY"),"") -> Dec 1899
F11: =IFERROR(TEXT(A11,"MMM YYYY"),"") -> Dec 1899
F12: =IFERROR(TEXT(A12,"MMM YYYY"),"") -> Dec 1899
F13: =IFERROR(TEXT(A13,"MMM YYYY"),"") -> Dec 1899
F14: =IFERROR(TEXT(A14,"MMM YYYY"),"") -> Dec 1899
F15: =IFERROR(TEXT(A15,"MMM YYYY"),"") -> Dec 1899
F16: =IFERROR(TEXT(A16,"MMM YYYY"),"") -> Dec 1899
F17: =IFERROR(TEXT(A17,"MMM YYYY"),"") -> Dec 1899
F18: =IFERROR(TEXT(A18,"MMM YYYY"),"") -> Dec 1899
F19: =IFERROR(TEXT(A19,"MMM YYYY"),"") -> Dec 1899
... F107: =IFERROR(TEXT(A107,"MMM YYYY"),"") -> Dec 1899
C109: TOTAL INCOME | D109: =SUM(D4:D108) -> 574.72

Sheet 💸 Expense Log
A1: 💸 EXPENSE LOG — Log every dollar the business spends
A2: Keep receipts for everything — all business expenses are potentially tax deductible
A3: DATE | B3: CATEGORY | C3: VENDOR | D3: AMOUNT ($) | E3: TAX DEDUCTIBLE? | F3: RECEIPT? | G3: MONTH | H3: DESCRIPTION
A4: 46174 | B4: Hosting/Infrastructure | C4: Supabase | D4: 0 | E4: Yes | F4: Yes | G4: =IFERROR(TEXT(A4,"MMM YYYY"),"") -> Jun 2026 | H4: Free tier — upgrade when needed
A5: 46174 | B5: App Store Fees | C5: Apple Developer | D5: 8.25 | E5: Yes | F5: Yes | G5: =IFERROR(TEXT(A5,"MMM YYYY"),"") -> Jun 2026 | H5: $99/yr annual fee
A6: 46176 | B6: Transaction Fees | C6: Stripe | D6: 12.47 | E6: Yes | F6: Auto | G6: =IFERROR(TEXT(A6,"MMM YYYY"),"") -> Jun 2026 | H6: 2.9% + 30¢ on ticket sales
A7: 46183 | B7: Software/Tools | C7: Buffer | D7: 0 | E7: Yes | F7: Yes | G7: =IFERROR(TEXT(A7,"MMM YYYY"),"") -> Jun 2026 | H7: Free tier social scheduling
G8: =IFERROR(TEXT(A8,"MMM YYYY"),"") -> Dec 1899
G9: =IFERROR(TEXT(A9,"MMM YYYY"),"") -> Dec 1899
G10: =IFERROR(TEXT(A10,"MMM YYYY"),"") -> Dec 1899
G11: =IFERROR(TEXT(A11,"MMM YYYY"),"") -> Dec 1899
G12: =IFERROR(TEXT(A12,"MMM YYYY"),"") -> Dec 1899
G13: =IFERROR(TEXT(A13,"MMM YYYY"),"") -> Dec 1899
G14: =IFERROR(TEXT(A14,"MMM YYYY"),"") -> Dec 1899
G15: =IFERROR(TEXT(A15,"MMM YYYY"),"") -> Dec 1899
G16: =IFERROR(TEXT(A16,"MMM YYYY"),"") -> Dec 1899
G17: =IFERROR(TEXT(A17,"MMM YYYY"),"") -> Dec 1899
G18: =IFERROR(TEXT(A18,"MMM YYYY"),"") -> Dec 1899
G19: =IFERROR(TEXT(A19,"MMM YYYY"),"") -> Dec 1899
... G107: =IFERROR(TEXT(A107,"MMM YYYY"),"") -> Dec 1899
C109: TOTAL EXPENSES | D109: =SUM(D4:D108) -> 20.72

Sheet 🪣 Tax Tracker
A1: 🪣 TAX TRACKER — Log every time you move money to your tax savings account
A2: Rule: Every time income comes in → immediately move 30% to a separate savings account → log it here
A3: DATE | B3: INCOME RECEIVED | C3: 30% TRANSFERRED | D3: FROM ACCOUNT | E3: QUARTER | F3: NOTES
A4: 46174 | B4: 337.5 | C4: 101.25 | D4: Business Checking → Tax Savings | E4: Q2
A5: 46176 | B5: 24 | C5: 7.2 | D5: Business Checking → Tax Savings | E5: Q2
A6: 46181 | B6: 48.22 | C6: 14.47 | D6: Business Checking → Tax Savings | E6: Q2
B107: TOTAL INCOME TRACKED | C107: =SUM(C4:C106) -> 122.92

Sheet 💰 Owner Draw
A1: 💰 OWNER'S DRAW — Every time you pay yourself, log it here
A2: This is not a salary — it's an owner's draw. You transfer from business account to personal account.
A3: DATE | B3: AMOUNT ($) | C3: FROM ACCOUNT | D3: TO ACCOUNT | E3: MONTH | F3: NOTES
A4: 46188 | B4: 800 | C4: The Bradley Project LLC Checking | D4: Personal Checking | E4: June 2026 | F4: Bi-monthly draw
A105: TOTAL DRAWN YTD | B105: =SUM(B4:B104) -> 800

Sheet 🏦 Reserve Fund
A1: 🏦 RESERVE FUND — 3 months of operating costs, sitting in the business account untouched
A2: Goal: 3 months of average expenses. Do NOT spend this. It is your emergency cushion.
A4: Average Monthly Expenses: | B4: =IFERROR(SUMPRODUCT((YEAR('💸 Expense Log'!A:A)='📊 Dashboard'!B5)*'💸 Expense Log'!D:D)/MAX(1,SUMPRODUCT((YEAR('💸 Expense Log'!A:A)='📊 Dashboard'!B5)*('💸 Expense Log'!D:D<>"")*(ROW('💸 Expense Log'!A:A)>3)/MAX(1,MONTH('💸 Expense Log'!A:A)))),0) -> 0 | D4: STATUS: | E4: =IF(B7>=1,"✅ FULLY FUNDED",IF(B7>=0.5,"⚡ HALFWAY THERE — KEEP GOING","🔴 NOT YET FUNDED — PRIORITY 1")) -> 🔴 NOT YET FUNDED — PRIORITY 1
A5: Reserve Target (3 months): | B5: =B4*3 -> 0
A6: Current Reserve Balance: | B6: =SUM(C10:C110) -> 200
A7: Funded %: | B7: =IFERROR(B6/B5,0) -> 0
A9: DATE | B9: ACTION | C9: AMOUNT ($) | D9: RUNNING BALANCE | E9: NOTES
A10: 46174 | B10: Initial deposit | C10: 200 | D10: =C10 -> 200 | E10: First contribution toward 3-month reserve goal
D11: =IFERROR(D10+C11,D10) -> 200
D12: =IFERROR(D11+C12,D11) -> 200
D13: =IFERROR(D12+C13,D12) -> 200
D14: =IFERROR(D13+C14,D13) -> 200
D15: =IFERROR(D14+C15,D14) -> 200
D16: =IFERROR(D15+C16,D15) -> 200
D17: =IFERROR(D16+C17,D16) -> 200
D18: =IFERROR(D17+C18,D17) -> 200
D19: =IFERROR(D18+C19,D18) -> 200
D20: =IFERROR(D19+C20,D19) -> 200
D21: =IFERROR(D20+C21,D20) -> 200
D22: =IFERROR(D21+C22,D21) -> 200
... D110: =IFERROR(D109+C110,D109) -> 200

Sheet 📈 Monthly P&L
A1: 📈 MONTHLY PROFIT & LOSS — Auto-calculated from Income and Expense logs
A2: Line Item | B2: Jan | C2: Feb | D2: Mar | E2: Apr | F2: May | G2: Jun | H2: Jul | I2: Aug | J2: Sep | K2: Oct | L2: Nov | M2: Dec | N2: ANNUAL TOTAL
A3: INCOME
A4: Gross Revenue | B4: =IFERROR(SUMPRODUCT((MONTH('📥 Income Log'!A:A)=1)*(YEAR('📥 Income Log'!A:A)='📊 Dashboard'!B5)*'📥 Income Log'!D:D),0) -> 0 | C4: =IFERROR(SUMPRODUCT((MONTH('📥 Income Log'!A:A)=2)*(YEAR('📥 Income Log'!A:A)='📊 Dashboard'!B5)*'📥 Income Log'!D:D),0) -> 0 | D4: =IFERROR(SUMPRODUCT((MONTH('📥 Income Log'!A:A)=3)*(YEAR('📥 Income Log'!A:A)='📊 Dashboard'!B5)*'📥 Income Log'!D:D),0) -> 0 | E4: =IFERROR(SUMPRODUCT((MONTH('📥 Income Log'!A:A)=4)*(YEAR('📥 Income Log'!A:A)='📊 Dashboard'!B5)*'📥 Income Log'!D:D),0) -> 0 | F4: =IFERROR(SUMPRODUCT((MONTH('📥 Income Log'!A:A)=5)*(YEAR('📥 Income Log'!A:A)='📊 Dashboard'!B5)*'📥 Income Log'!D:D),0) -> 0 | G4: =IFERROR(SUMPRODUCT((MONTH('📥 Income Log'!A:A)=6)*(YEAR('📥 Income Log'!A:A)='📊 Dashboard'!B5)*'📥 Income Log'!D:D),0) -> 0 | H4: =IFERROR(SUMPRODUCT((MONTH('📥 Income Log'!A:A)=7)*(YEAR('📥 Income Log'!A:A)='📊 Dashboard'!B5)*'📥 Income Log'!D:D),0) -> 0 | I4: =IFERROR(SUMPRODUCT((MONTH('📥 Income Log'!A:A)=8)*(YEAR('📥 Income Log'!A:A)='📊 Dashboard'!B5)*'📥 Income Log'!D:D),0) -> 0 | J4: =IFERROR(SUMPRODUCT((MONTH('📥 Income Log'!A:A)=9)*(YEAR('📥 Income Log'!A:A)='📊 Dashboard'!B5)*'📥 Income Log'!D:D),0) -> 0 | K4: =IFERROR(SUMPRODUCT((MONTH('📥 Income Log'!A:A)=10)*(YEAR('📥 Income Log'!A:A)='📊 Dashboard'!B5)*'📥 Income Log'!D:D),0) -> 0 | L4: =IFERROR(SUMPRODUCT((MONTH('📥 Income Log'!A:A)=11)*(YEAR('📥 Income Log'!A:A)='📊 Dashboard'!B5)*'📥 Income Log'!D:D),0) -> 0 | M4: =IFERROR(SUMPRODUCT((MONTH('📥 Income Log'!A:A)=12)*(YEAR('📥 Income Log'!A:A)='📊 Dashboard'!B5)*'📥 Income Log'!D:D),0) -> 0 | N4: =SUM(B4:M4) -> 0
A6: DEDUCTIONS
A7: Taxes (30%) | B7: =B4*'📊 Dashboard'!F5 -> 0 | C7: =C4*'📊 Dashboard'!F5 -> 0 | D7: =D4*'📊 Dashboard'!F5 -> 0 | E7: =E4*'📊 Dashboard'!F5 -> 0 | F7: =F4*'📊 Dashboard'!F5 -> 0 | G7: =G4*'📊 Dashboard'!F5 -> 0 | H7: =H4*'📊 Dashboard'!F5 -> 0 | I7: =I4*'📊 Dashboard'!F5 -> 0 | J7: =J4*'📊 Dashboard'!F5 -> 0 | K7: =K4*'📊 Dashboard'!F5 -> 0 | L7: =L4*'📊 Dashboard'!F5 -> 0 | M7: =M4*'📊 Dashboard'!F5 -> 0 | N7: =SUM(B7:M7) -> 0
A8: Operating Expenses | B8: =IFERROR(SUMPRODUCT((MONTH('💸 Expense Log'!A:A)=1)*(YEAR('💸 Expense Log'!A:A)='📊 Dashboard'!B5)*'💸 Expense Log'!D:D),0) -> 0 | C8: =IFERROR(SUMPRODUCT((MONTH('💸 Expense Log'!A:A)=2)*(YEAR('💸 Expense Log'!A:A)='📊 Dashboard'!B5)*'💸 Expense Log'!D:D),0) -> 0 | D8: =IFERROR(SUMPRODUCT((MONTH('💸 Expense Log'!A:A)=3)*(YEAR('💸 Expense Log'!A:A)='📊 Dashboard'!B5)*'💸 Expense Log'!D:D),0) -> 0 | E8: =IFERROR(SUMPRODUCT((MONTH('💸 Expense Log'!A:A)=4)*(YEAR('💸 Expense Log'!A:A)='📊 Dashboard'!B5)*'💸 Expense Log'!D:D),0) -> 0 | F8: =IFERROR(SUMPRODUCT((MONTH('💸 Expense Log'!A:A)=5)*(YEAR('💸 Expense Log'!A:A)='📊 Dashboard'!B5)*'💸 Expense Log'!D:D),0) -> 0 | G8: =IFERROR(SUMPRODUCT((MONTH('💸 Expense Log'!A:A)=6)*(YEAR('💸 Expense Log'!A:A)='📊 Dashboard'!B5)*'💸 Expense Log'!D:D),0) -> 0 | H8: =IFERROR(SUMPRODUCT((MONTH('💸 Expense Log'!A:A)=7)*(YEAR('💸 Expense Log'!A:A)='📊 Dashboard'!B5)*'💸 Expense Log'!D:D),0) -> 0 | I8: =IFERROR(SUMPRODUCT((MONTH('💸 Expense Log'!A:A)=8)*(YEAR('💸 Expense Log'!A:A)='📊 Dashboard'!B5)*'💸 Expense Log'!D:D),0) -> 0 | J8: =IFERROR(SUMPRODUCT((MONTH('💸 Expense Log'!A:A)=9)*(YEAR('💸 Expense Log'!A:A)='📊 Dashboard'!B5)*'💸 Expense Log'!D:D),0) -> 0 | K8: =IFERROR(SUMPRODUCT((MONTH('💸 Expense Log'!A:A)=10)*(YEAR('💸 Expense Log'!A:A)='📊 Dashboard'!B5)*'💸 Expense Log'!D:D),0) -> 0 | L8: =IFERROR(SUMPRODUCT((MONTH('💸 Expense Log'!A:A)=11)*(YEAR('💸 Expense Log'!A:A)='📊 Dashboard'!B5)*'💸 Expense Log'!D:D),0) -> 0 | M8: =IFERROR(SUMPRODUCT((MONTH('💸 Expense Log'!A:A)=12)*(YEAR('💸 Expense Log'!A:A)='📊 Dashboard'!B5)*'💸 Expense Log'!D:D),0) -> 0 | N8: =SUM(B8:M8) -> 0
A9: Reinvestment (15%) | B9: =(B4-B6-B7)*'📊 Dashboard'!H5 -> 0 | C9: =(C4-C6-C7)*'📊 Dashboard'!H5 -> 0 | D9: =(D4-D6-D7)*'📊 Dashboard'!H5 -> 0 | E9: =(E4-E6-E7)*'📊 Dashboard'!H5 -> 0 | F9: =(F4-F6-F7)*'📊 Dashboard'!H5 -> 0 | G9: =(G4-G6-G7)*'📊 Dashboard'!H5 -> 0 | H9: =(H4-H6-H7)*'📊 Dashboard'!H5 -> 0 | I9: =(I4-I6-I7)*'📊 Dashboard'!H5 -> 0 | J9: =(J4-J6-J7)*'📊 Dashboard'!H5 -> 0 | K9: =(K4-K6-K7)*'📊 Dashboard'!H5 -> 0 | L9: =(L4-L6-L7)*'📊 Dashboard'!H5 -> 0 | M9: =(M4-M6-M7)*'📊 Dashboard'!H5 -> 0 | N9: =SUM(B9:M9) -> 0
A11: RESULTS
A12: Owner Take-Home | B12: =B4-B6-B7-B8 -> 0 | C12: =C4-C6-C7-C8 -> 0 | D12: =D4-D6-D7-D8 -> 0 | E12: =E4-E6-E7-E8 -> 0 | F12: =F4-F6-F7-F8 -> 0 | G12: =G4-G6-G7-G8 -> 0 | H12: =H4-H6-H7-H8 -> 0 | I12: =I4-I6-I7-I8 -> 0 | ... M12: =M4-M6-M7-M8 -> 0 | N12: =SUM(B12:M12) -> 0
A13: Profit Margin % | B13: =IFERROR(B11/B4,0) -> 0 | C13: =IFERROR(C11/C4,0) -> 0 | D13: =IFERROR(D11/D4,0) -> 0 | E13: =IFERROR(E11/E4,0) -> 0 | F13: =IFERROR(F11/F4,0) -> 0 | G13: =IFERROR(G11/G4,0) -> 0 | H13: =IFERROR(H11/H4,0) -> 0 | I13: =IFERROR(I11/I4,0) -> 0 | ... M13: =IFERROR(M11/M4,0) -> 0 | N13: =SUM(B13:M13) -> 0
A14: Cumulative YTD Revenue | B14: =B4 -> 0 | C14: =B14+C4 -> 0 | D14: =C14+D4 -> 0 | E14: =D14+E4 -> 0 | F14: =E14+F4 -> 0 | G14: =F14+G4 -> 0 | H14: =G14+H4 -> 0 | I14: =H14+I4 -> 0 | J14: =I14+J4 -> 0 | ... M14: =L14+M4 -> 0 | N14: =SUM(B14:M14) -> 0
